{
  "project_info": {
    "project_number": "700837754100",
    "project_id": "unibuc-f7941",
    "storage_bucket": "unibuc-f7941.appspot.com"
  },
  "client": [
    {
      "client_info": {
        "mobilesdk_app_id": "1:700837754100:android:ecba276cdc8874409fdaa1",
        "android_client_info": {
          "package_name": "com.mihaialexandruteodor406.unibuc"
        }
      },
      "oauth_client": [
        {
          "client_id": "700837754100-filfjasjldmo4guil577dvspmbb5n8i1.apps.googleusercontent.com",
          "client_type": 3
        }
      ],
      "api_key": [
        {
          "current_key": "AIzaSyBttoOl-8os81J0s2CJw_4i3amshAG-VR8"
        }
      ],
      "services": {
        "appinvite_service": {
          "other_platform_oauth_client": [
            {
              "client_id": "700837754100-filfjasjldmo4guil577dvspmbb5n8i1.apps.googleusercontent.com",
              "client_type": 3
            }
          ]
        }
      }
    }
  ],
  "configuration_version": "1"
}